pygestpay/__init__.py
pygestpay/currencies.py
pygestpay/gestpay.py
python_gestpay-2.1.0.dist-info/METADATA
python_gestpay-2.1.0.dist-info/WHEEL
python_gestpay-2.1.0.dist-info/top_level.txt
python_gestpay-2.1.0.dist-info/RECORD
