Metadata-Version: 2.1
Name: python-gestpay
Version: 2.1.0
Summary: Gestpay WSs2s and WsCryptDecrypt SOAP Client
Home-page: https://github.com/metadonors/python-gestpay
Author: Metadonors
Author-email: services@metadonors.it
License: MIT
Platform: UNKNOWN
Requires-Dist: zeep
